abx_plugin_sqlitefts_search/__init__.py
abx_plugin_sqlitefts_search/config.py
abx_plugin_sqlitefts_search/searchbackend.py
abx_plugin_sqlitefts_search-2024.10.28.dist-info/METADATA
abx_plugin_sqlitefts_search-2024.10.28.dist-info/WHEEL
abx_plugin_sqlitefts_search-2024.10.28.dist-info/entry_points.txt
abx_plugin_sqlitefts_search-2024.10.28.dist-info/RECORD
